[
  {
    "id": 1,
    "question": "What HTML element is used to create an unordered list?",
    "correct": 1,
    "choices": [
      {
        "id": 1,
        "answer": "<ul>"
      },
      {
        "id": 2,
        "answer": "<ol>"
      },
      {
        "id": 3,
        "answer": "<li>"
      },
      {
        "id": 4,
        "answer": "<dl>"
      }
    ]
  },
  {
    "id": 2,
    "question": "What HTML element is used to create a list item within a list?",
    "correct": 3,
    "choices": [
      {
        "id": 1,
        "answer": "<ul>"
      },
      {
        "id": 2,
        "answer": "<ol>"
      },
      {
        "id": 3,
        "answer": "<li>"
      },
      {
        "id": 4,
        "answer": "<dl>"
      }
    ]
  },
  {
    "id": 3,
    "question": "How would you create a nested unordered list?",
    "correct": 1,
    "choices": [
      {
        "id": 1,
        "answer": "Wrap an unordered list within a list item of another unordered list"
      },
      {
        "id": 2,
        "answer": "Wrap an ordered list within a list item of another unordered list"
      },
      {
        "id": 3,
        "answer": "Wrap a list item within a list item of another unordered list"
      },
      {
        "id": 4,
        "answer": "Wrap a list item within a list item of an ordered list"
      }
    ]
  },
  {
    "id": 4,
    "question": "How do you customize the bullet style of an unordered list using CSS?",
    "correct": 4,
    "choices": [
      {
        "id": 1,
        "answer": "ul { list-style-type: circle; }"
      },
      {
        "id": 2,
        "answer": "ul { list-style-type: disc; }"
      },
      {
        "id": 3,
        "answer": "ul { list-style-type: square; }"
      },
      {
        "id": 4,
        "answer": "ul { list-style-type: none; }"
      }
    ]
  },
  {
    "id": 5,
    "question": "What HTML element is used to create an ordered list?",
    "correct": 2,
    "choices": [
      {
        "id": 1,
        "answer": "<ul>"
      },
      {
        "id": 2,
        "answer": "<ol>"
      },
      {
        "id": 3,
        "answer": "<li>"
      },
      {
        "id": 4,
        "answer": "<dl>"
      }
    ]
  },
  {
    "id": 6,
    "question": "What HTML element is used to create a description list?",
    "correct": 4,
    "choices": [
      {
        "id": 1,
        "answer": "<ul>"
      },
      {
        "id": 2,
        "answer": "<ol>"
      },
      {
        "id": 3,
        "answer": "<li>"
      },
      {
        "id": 4,
        "answer": "<dl>"
      }
    ]
  },
  {
    "id": 7,
    "question": "What HTML element is used to define a term in a description list?",
    "correct": 1,
    "choices": [
      {
        "id": 1,
        "answer": "<dt>"
      },
      {
        "id": 2,
        "answer": "<dd>"
      },
      {
        "id": 3,
        "answer": "<dl>"
      },
      {
        "id": 4,
        "answer": "<li>"
      }
    ]
  },
  {
    "id": 8,
    "question": "What CSS property is used to change the numbering style of an ordered list?",
    "correct": 3,
    "choices": [
      {
        "id": 1,
        "answer": "list-style-image"
      },
      {
        "id": 2,
        "answer": "list-style"
      },
      {
        "id": 3,
        "answer": "list-style-type"
      },
      {
        "id": 4,
        "answer": "list-type"
      }
    ]
  },
  {
    "id": 9,
    "question": "How do you create a nested ordered list?",
    "correct": 4,
    "choices": [
      {
        "id": 1,
        "answer": "Wrap an unordered list within a list item of another ordered list"
      },
      {
        "id": 2,
        "answer": "Wrap an unordered list within a list item of another unordered list"
      },
      {
        "id": 3,
        "answer": "Wrap a list item within a list item of another ordered list"
      },
      {
        "id": 4,
        "answer": "Wrap an ordered list within a list item of another ordered list"
      }
    ]
  },
  {
    "id": 10,
    "question": "What HTML element is used to create a sublist in an ordered list?",
    "correct": 3,
    "choices": [
      {
        "id": 1,
        "answer": "<dl>"
      },
      {
        "id": 2,
        "answer": "<li>"
      },
      {
        "id": 3,
        "answer": "<ol>"
      },
      {
        "id": 4,
        "answer": "<ul>"
      }
    ]
  }
]
